odoo/addons/base_external_mssql/LICENSE
odoo/addons/base_external_mssql/README.rst
odoo/addons/base_external_mssql/__init__.py
odoo/addons/base_external_mssql/__manifest__.py
odoo/addons/base_external_mssql/images/screen.png
odoo/addons/base_external_mssql/models/__init__.py
odoo/addons/base_external_mssql/models/base_external_mssql.py
odoo/addons/base_external_mssql/security/ir.model.access.csv
odoo/addons/base_external_mssql/static/description/icon.png
odoo/addons/base_external_mssql/static/description/index.html
odoo/addons/base_external_mssql/static/src/css/style.css
odoo/addons/base_external_mssql/static/src/js/widget.js
odoo/addons/base_external_mssql/tests/TEST_INSTRUCTIONS.rst
odoo/addons/base_external_mssql/tests/__init__.py
odoo/addons/base_external_mssql/tests/test_db.py
odoo/addons/base_external_mssql/views/base_external_mssql.xml
odoo_addon_base_external_mssql-18.0.1.0.0.13.dist-info/METADATA
odoo_addon_base_external_mssql-18.0.1.0.0.13.dist-info/WHEEL
odoo_addon_base_external_mssql-18.0.1.0.0.13.dist-info/top_level.txt
odoo_addon_base_external_mssql-18.0.1.0.0.13.dist-info/RECORD
