Metadata-Version: 2.1
Name: odoo-addon-base_external_mssql
Version: 18.0.1.0.0.13
Requires-Python: >=3.10
Requires-Dist: odoo==18.0.*
Summary: Establish connection to external mssql database.
Home-page: https://www.mint-system.ch/
License: AGPL-3
Author: Mint System GmbH
Classifier: Programming Language :: Python
Classifier: Framework :: Odoo
Classifier: Framework :: Odoo :: 18.0
Classifier: License :: OSI Approved :: GNU Affero General Public License v3
